tdp_dummy/__init__.py
tdp_dummy/config.json
tdp_dummy/sql.py
tdp_dummy-9.0.1.dist-info/LICENSE
tdp_dummy-9.0.1.dist-info/METADATA
tdp_dummy-9.0.1.dist-info/WHEEL
tdp_dummy-9.0.1.dist-info/entry_points.txt
tdp_dummy-9.0.1.dist-info/top_level.txt
tdp_dummy-9.0.1.dist-info/RECORD
