Metadata-Version: 2.1
Name: tdp-dummy
Version: 9.0.1
Summary: UNKNOWN
Home-page: https://phovea.caleydo.org
Author: The Caleydo Team
Author-email: contact@caleydo.org
License: BSD-3-Clause
Platform: UNKNOWN
Classifier: Intended Audience :: Developers
Classifier: Operating System :: OS Independent
Classifier: License :: OSI Approved :: BSD License
Classifier: Programming Language :: Python
Classifier: Programming Language :: Python :: 3.7
Requires-Dist: tdp-core (<12.0.0,>=11.0.0)
